{  "data":[{  "name": "A - Marina",  "date": "2016/03/14",  "duration": "5404",  "repsPerSet": "14-18",  "rest": "49",  "exercises": [{"name": "Extensora", "sets": "6", "weight": "0"}, {"name": "Leg Press 45º", "sets": "6", "weight": "0"}, {"name": "Agachamento smith ou guiado", "sets": "6", "weight": "0"}, {"name": "Agachamento no rack", "sets": "6", "weight": "0"}, {"name": "Adutor", "sets": "6", "weight": "0"}, {"name": "Peck deck", "sets": "6", "weight": "0"}, {"name": "Supino inclinado", "sets": "6", "weight": "0"}, {"name": "Supino reto", "sets": "6", "weight": "0"}, {"name": "Rosca direta ou alternada", "sets": "6", "weight": "0"}  ]},{  "name": "B - Marina",  "date": "2016/03/16",  "duration": "4603",  "repsPerSet": "14-18",  "rest": "49",  "exercises": [{"name": "Flexora", "sets": "4", "weight": "21"}, {"name": "Glúteo em pé", "sets": "4", "weight": "0"}, {"name": "Glúteo no cabo", "sets": "4", "weight": "0"}, {"name": "Abdutor", "sets": "4", "weight": "0"}, {"name": "Agachamento sumo", "sets": "4", "weight": "0"}, {"name": "Stiff", "sets": "4", "weight": "0"}, {"name": "Remada articulada", "sets": "4", "weight": "0"}, {"name": "Tríceps na polia", "sets": "4", "weight": "0"}, {"name": "Tríceps corda", "sets": "4", "weight": "0"}, {"name": "Panturrilha", "sets": "4", "weight": "0"}, {"name": "Puxador frente", "sets": "3", "weight": "0"}, {"name": "Remada baixa", "sets": "3", "weight": "0"}  ]},{  "name": "A - Marina",  "date": "2016/03/21",  "duration": "3903",  "repsPerSet": "14-18",  "rest": "49",  "exercises": [{"name": "Extensora", "sets": "5", "weight": "0"}, {"name": "Leg Press 45º", "sets": "5", "weight": "0"}, {"name": "Agachamento smith ou guiado", "sets": "5", "weight": "0"}, {"name": "Agachamento no rack", "sets": "4", "weight": "0"}, {"name": "Adutor", "sets": "4", "weight": "0"}, {"name": "Peck deck", "sets": "4", "weight": "0"}, {"name": "Supino inclinado", "sets": "4", "weight": "0"}, {"name": "Supino reto", "sets": "4", "weight": "0"}, {"name": "Rosca direta ou alternada", "sets": "4", "weight": "0"}  ]},{  "name": "B - Marina",  "date": "2016/03/23",  "duration": "3102",  "repsPerSet": "14-18",  "rest": "49",  "exercises": [{"name": "Flexora", "sets": "3", "weight": "21"}, {"name": "Glúteo em pé", "sets": "3", "weight": "0"}, {"name": "Glúteo no cabo", "sets": "3", "weight": "0"}, {"name": "Abdutor", "sets": "3", "weight": "0"}, {"name": "Agachamento sumo", "sets": "3", "weight": "0"}, {"name": "Stiff", "sets": "3", "weight": "0"}, {"name": "Remada articulada", "sets": "3", "weight": "0"}, {"name": "Tríceps na polia", "sets": "2", "weight": "0"}, {"name": "Tríceps corda", "sets": "2", "weight": "0"}, {"name": "Panturrilha", "sets": "2", "weight": "0"}, {"name": "Puxador frente", "sets": "2", "weight": "0"}, {"name": "Remada baixa", "sets": "2", "weight": "0"}  ]},{  "name": "A - Marina",  "date": "2016/03/28",  "duration": "5400",  "repsPerSet": "12-16",  "rest": "37",  "exercises": [{"name": "Extensora", "sets": "8", "weight": "0"}, {"name": "Leg Press 45º", "sets": "8", "weight": "0"}, {"name": "Agachamento smith ou guiado", "sets": "8", "weight": "0"}, {"name": "Agachamento no rack", "sets": "7", "weight": "0"}, {"name": "Adutor", "sets": "7", "weight": "0"}, {"name": "Peck deck", "sets": "7", "weight": "0"}, {"name": "Supino inclinado", "sets": "7", "weight": "0"}, {"name": "Supino reto", "sets": "7", "weight": "0"}, {"name": "Rosca direta ou alternada", "sets": "7", "weight": "0"}  ]},{  "name": "B - Marina",  "date": "2016/03/30",  "duration": "4582",  "repsPerSet": "12-16",  "rest": "37",  "exercises": [{"name": "Flexora", "sets": "5", "weight": "22"}, {"name": "Glúteo em pé", "sets": "5", "weight": "0"}, {"name": "Glúteo no cabo", "sets": "5", "weight": "0"}, {"name": "Abdutor", "sets": "5", "weight": "0"}, {"name": "Agachamento sumo", "sets": "5", "weight": "0"}, {"name": "Stiff", "sets": "5", "weight": "0"}, {"name": "Remada articulada", "sets": "5", "weight": "0"}, {"name": "Tríceps na polia", "sets": "5", "weight": "0"}, {"name": "Tríceps corda", "sets": "4", "weight": "0"}, {"name": "Panturrilha", "sets": "4", "weight": "0"}, {"name": "Puxador frente", "sets": "4", "weight": "0"}, {"name": "Remada baixa", "sets": "4", "weight": "0"}  ]},{  "name": "A - Marina",  "date": "2016/04/04",  "duration": "3845",  "repsPerSet": "12-16",  "rest": "37",  "exercises": [{"name": "Extensora", "sets": "6", "weight": "0"}, {"name": "Leg Press 45º", "sets": "6", "weight": "0"}, {"name": "Agachamento smith ou guiado", "sets": "5", "weight": "0"}, {"name": "Agachamento no rack", "sets": "5", "weight": "0"}, {"name": "Adutor", "sets": "5", "weight": "0"}, {"name": "Peck deck", "sets": "5", "weight": "0"}, {"name": "Supino inclinado", "sets": "5", "weight": "0"}, {"name": "Supino reto", "sets": "5", "weight": "0"}, {"name": "Rosca direta ou alternada", "sets": "5", "weight": "0"}  ]},{  "name": "B - Marina",  "date": "2016/04/06",  "duration": "3109",  "repsPerSet": "12-16",  "rest": "37",  "exercises": [{"name": "Flexora", "sets": "4", "weight": "22"}, {"name": "Glúteo em pé", "sets": "4", "weight": "0"}, {"name": "Glúteo no cabo", "sets": "3", "weight": "0"}, {"name": "Abdutor", "sets": "3", "weight": "0"}, {"name": "Agachamento sumo", "sets": "3", "weight": "0"}, {"name": "Stiff", "sets": "3", "weight": "0"}, {"name": "Remada articulada", "sets": "3", "weight": "0"}, {"name": "Tríceps na polia", "sets": "3", "weight": "0"}, {"name": "Tríceps corda", "sets": "3", "weight": "0"}, {"name": "Panturrilha", "sets": "3", "weight": "0"}, {"name": "Puxador frente", "sets": "3", "weight": "0"}, {"name": "Remada baixa", "sets": "3", "weight": "0"}  ]},{  "name": "A - Marina",  "date": "2016/04/11",  "duration": "3203",  "repsPerSet": "9-13",  "rest": "31",  "exercises": [{"name": "Extensora", "sets": "6", "weight": "0"}, {"name": "Leg Press 45º", "sets": "6", "weight": "0"}, {"name": "Agachamento smith ou guiado", "sets": "6", "weight": "0"}, {"name": "Agachamento no rack", "sets": "5", "weight": "0"}, {"name": "Adutor", "sets": "5", "weight": "0"}, {"name": "Peck deck", "sets": "5", "weight": "0"}, {"name": "Supino inclinado", "sets": "5", "weight": "0"}, {"name": "Supino reto", "sets": "5", "weight": "0"}, {"name": "Rosca direta ou alternada", "sets": "5", "weight": "0"}  ]},{  "name": "B - Marina",  "date": "2016/04/13",  "duration": "1868",  "repsPerSet": "9-13",  "rest": "31",  "exercises": [{"name": "Flexora", "sets": "3", "weight": "23"}, {"name": "Glúteo em pé", "sets": "3", "weight": "0"}, {"name": "Glúteo no cabo", "sets": "3", "weight": "0"}, {"name": "Abdutor", "sets": "3", "weight": "0"}, {"name": "Agachamento sumo", "sets": "2", "weight": "0"}, {"name": "Stiff", "sets": "2", "weight": "0"}, {"name": "Remada articulada", "sets": "2", "weight": "0"}, {"name": "Tríceps na polia", "sets": "2", "weight": "0"}, {"name": "Tríceps corda", "sets": "2", "weight": "0"}, {"name": "Panturrilha", "sets": "2", "weight": "0"}, {"name": "Puxador frente", "sets": "2", "weight": "0"}, {"name": "Remada baixa", "sets": "2", "weight": "0"}  ]},{  "name": "A - Marina",  "date": "2016/04/18",  "duration": "2736",  "repsPerSet": "9-13",  "rest": "31",  "exercises": [{"name": "Extensora", "sets": "5", "weight": "0"}, {"name": "Leg Press 45º", "sets": "5", "weight": "0"}, {"name": "Agachamento smith ou guiado", "sets": "5", "weight": "0"}, {"name": "Agachamento no rack", "sets": "5", "weight": "0"}, {"name": "Adutor", "sets": "5", "weight": "0"}, {"name": "Peck deck", "sets": "4", "weight": "0"}, {"name": "Supino inclinado", "sets": "4", "weight": "0"}, {"name": "Supino reto", "sets": "4", "weight": "0"}, {"name": "Rosca direta ou alternada", "sets": "4", "weight": "0"}  ]},{  "name": "B - Marina",  "date": "2016/04/20",  "duration": "1401",  "repsPerSet": "9-13",  "rest": "31",  "exercises": [{"name": "Flexora", "sets": "2", "weight": "23"}, {"name": "Glúteo em pé", "sets": "2", "weight": "0"}, {"name": "Glúteo no cabo", "sets": "2", "weight": "0"}, {"name": "Abdutor", "sets": "2", "weight": "0"}, {"name": "Agachamento sumo", "sets": "2", "weight": "0"}, {"name": "Stiff", "sets": "2", "weight": "0"}, {"name": "Remada articulada", "sets": "2", "weight": "0"}, {"name": "Tríceps na polia", "sets": "2", "weight": "0"}, {"name": "Tríceps corda", "sets": "2", "weight": "0"}, {"name": "Panturrilha", "sets": "1", "weight": "0"}, {"name": "Puxador frente", "sets": "1", "weight": "0"}, {"name": "Remada baixa", "sets": "1", "weight": "0"}  ]},{  "name": "A - Marina",  "date": "2016/04/25",  "duration": "5412",  "repsPerSet": "9-13",  "rest": "30",  "exercises": [{"name": "Extensora", "sets": "10", "weight": "0"}, {"name": "Leg Press 45º", "sets": "9", "weight": "0"}, {"name": "Agachamento smith ou guiado", "sets": "9", "weight": "0"}, {"name": "Agachamento no rack", "sets": "9", "weight": "0"}, {"name": "Adutor", "sets": "9", "weight": "0"}, {"name": "Peck deck", "sets": "9", "weight": "0"}, {"name": "Supino inclinado", "sets": "9", "weight": "0"}, {"name": "Supino reto", "sets": "9", "weight": "0"}, {"name": "Rosca direta ou alternada", "sets": "9", "weight": "0"}  ]},{  "name": "B - Marina",  "date": "2016/04/27",  "duration": "4620",  "repsPerSet": "9-13",  "rest": "30",  "exercises": [{"name": "Flexora", "sets": "6", "weight": "23"}, {"name": "Glúteo em pé", "sets": "6", "weight": "0"}, {"name": "Glúteo no cabo", "sets": "6", "weight": "0"}, {"name": "Abdutor", "sets": "6", "weight": "0"}, {"name": "Agachamento sumo", "sets": "6", "weight": "0"}, {"name": "Stiff", "sets": "6", "weight": "0"}, {"name": "Remada articulada", "sets": "6", "weight": "0"}, {"name": "Tríceps na polia", "sets": "6", "weight": "0"}, {"name": "Tríceps corda", "sets": "6", "weight": "0"}, {"name": "Panturrilha", "sets": "6", "weight": "0"}, {"name": "Puxador frente", "sets": "5", "weight": "0"}, {"name": "Remada baixa", "sets": "5", "weight": "0"}  ]},{  "name": "A - Marina",  "date": "2016/05/02",  "duration": "3828",  "repsPerSet": "9-13",  "rest": "30",  "exercises": [{"name": "Extensora", "sets": "7", "weight": "0"}, {"name": "Leg Press 45º", "sets": "7", "weight": "0"}, {"name": "Agachamento smith ou guiado", "sets": "7", "weight": "0"}, {"name": "Agachamento no rack", "sets": "7", "weight": "0"}, {"name": "Adutor", "sets": "6", "weight": "0"}, {"name": "Peck deck", "sets": "6", "weight": "0"}, {"name": "Supino inclinado", "sets": "6", "weight": "0"}, {"name": "Supino reto", "sets": "6", "weight": "0"}, {"name": "Rosca direta ou alternada", "sets": "6", "weight": "0"}  ]},{  "name": "B - Marina",  "date": "2016/05/04",  "duration": "3102",  "repsPerSet": "9-13",  "rest": "30",  "exercises": [{"name": "Flexora", "sets": "4", "weight": "23"}, {"name": "Glúteo em pé", "sets": "4", "weight": "0"}, {"name": "Glúteo no cabo", "sets": "4", "weight": "0"}, {"name": "Abdutor", "sets": "4", "weight": "0"}, {"name": "Agachamento sumo", "sets": "4", "weight": "0"}, {"name": "Stiff", "sets": "4", "weight": "0"}, {"name": "Remada articulada", "sets": "4", "weight": "0"}, {"name": "Tríceps na polia", "sets": "4", "weight": "0"}, {"name": "Tríceps corda", "sets": "4", "weight": "0"}, {"name": "Panturrilha", "sets": "4", "weight": "0"}, {"name": "Puxador frente", "sets": "4", "weight": "0"}, {"name": "Remada baixa", "sets": "3", "weight": "0"}  ]},{  "name": "A - Marina",  "date": "2016/05/09",  "duration": "5786",  "repsPerSet": "8-12",  "rest": "32",  "exercises": [{"name": "Extensora", "sets": "10", "weight": "0"}, {"name": "Leg Press 45º", "sets": "10", "weight": "0"}, {"name": "Agachamento smith ou guiado", "sets": "10", "weight": "0"}, {"name": "Agachamento no rack", "sets": "10", "weight": "0"}, {"name": "Adutor", "sets": "10", "weight": "0"}, {"name": "Peck deck", "sets": "10", "weight": "0"}, {"name": "Supino inclinado", "sets": "10", "weight": "0"}, {"name": "Supino reto", "sets": "10", "weight": "0"}, {"name": "Rosca direta ou alternada", "sets": "9", "weight": "0"}  ]},{  "name": "B - Marina",  "date": "2016/05/11",  "duration": "4941",  "repsPerSet": "8-12",  "rest": "32",  "exercises": [{"name": "Flexora", "sets": "7", "weight": "24"}, {"name": "Glúteo em pé", "sets": "7", "weight": "0"}, {"name": "Glúteo no cabo", "sets": "7", "weight": "0"}, {"name": "Abdutor", "sets": "7", "weight": "0"}, {"name": "Agachamento sumo", "sets": "6", "weight": "0"}, {"name": "Stiff", "sets": "6", "weight": "0"}, {"name": "Remada articulada", "sets": "6", "weight": "0"}, {"name": "Tríceps na polia", "sets": "6", "weight": "0"}, {"name": "Tríceps corda", "sets": "6", "weight": "0"}, {"name": "Panturrilha", "sets": "6", "weight": "0"}, {"name": "Puxador frente", "sets": "6", "weight": "0"}, {"name": "Remada baixa", "sets": "6", "weight": "0"}  ]},{  "name": "A - Marina",  "date": "2016/05/16",  "duration": "4161",  "repsPerSet": "8-12",  "rest": "32",  "exercises": [{"name": "Extensora", "sets": "8", "weight": "0"}, {"name": "Leg Press 45º", "sets": "7", "weight": "0"}, {"name": "Agachamento smith ou guiado", "sets": "7", "weight": "0"}, {"name": "Agachamento no rack", "sets": "7", "weight": "0"}, {"name": "Adutor", "sets": "7", "weight": "0"}, {"name": "Peck deck", "sets": "7", "weight": "0"}, {"name": "Supino inclinado", "sets": "7", "weight": "0"}, {"name": "Supino reto", "sets": "7", "weight": "0"}, {"name": "Rosca direta ou alternada", "sets": "7", "weight": "0"}  ]},{  "name": "B - Marina",  "date": "2016/05/18",  "duration": "3315",  "repsPerSet": "8-12",  "rest": "32",  "exercises": [{"name": "Flexora", "sets": "5", "weight": "24"}, {"name": "Glúteo em pé", "sets": "5", "weight": "0"}, {"name": "Glúteo no cabo", "sets": "5", "weight": "0"}, {"name": "Abdutor", "sets": "4", "weight": "0"}, {"name": "Agachamento sumo", "sets": "4", "weight": "0"}, {"name": "Stiff", "sets": "4", "weight": "0"}, {"name": "Remada articulada", "sets": "4", "weight": "0"}, {"name": "Tríceps na polia", "sets": "4", "weight": "0"}, {"name": "Tríceps corda", "sets": "4", "weight": "0"}, {"name": "Panturrilha", "sets": "4", "weight": "0"}, {"name": "Puxador frente", "sets": "4", "weight": "0"}, {"name": "Remada baixa", "sets": "4", "weight": "0"}  ]},{  "name": "A - Marina",  "date": "2016/05/23",  "duration": "5898",  "repsPerSet": "8-12",  "rest": "39",  "exercises": [{"name": "Extensora", "sets": "10", "weight": "0"}, {"name": "Leg Press 45º", "sets": "9", "weight": "0"}, {"name": "Agachamento smith ou guiado", "sets": "9", "weight": "0"}, {"name": "Agachamento no rack", "sets": "9", "weight": "0"}, {"name": "Adutor", "sets": "9", "weight": "0"}, {"name": "Peck deck", "sets": "9", "weight": "0"}, {"name": "Supino inclinado", "sets": "9", "weight": "0"}, {"name": "Supino reto", "sets": "9", "weight": "0"}, {"name": "Rosca direta ou alternada", "sets": "9", "weight": "0"}  ]},{  "name": "B - Marina",  "date": "2016/05/25",  "duration": "6186",  "repsPerSet": "8-12",  "rest": "39",  "exercises": [{"name": "Flexora", "sets": "8", "weight": "24"}, {"name": "Glúteo em pé", "sets": "8", "weight": "0"}, {"name": "Glúteo no cabo", "sets": "7", "weight": "0"}, {"name": "Abdutor", "sets": "7", "weight": "0"}, {"name": "Agachamento sumo", "sets": "7", "weight": "0"}, {"name": "Stiff", "sets": "7", "weight": "0"}, {"name": "Remada articulada", "sets": "7", "weight": "0"}, {"name": "Tríceps na polia", "sets": "7", "weight": "0"}, {"name": "Tríceps corda", "sets": "7", "weight": "0"}, {"name": "Panturrilha", "sets": "7", "weight": "0"}, {"name": "Puxador frente", "sets": "7", "weight": "0"}, {"name": "Remada baixa", "sets": "7", "weight": "0"}  ]},{  "name": "A - Marina",  "date": "2016/05/30",  "duration": "6186",  "repsPerSet": "8-12",  "rest": "39",  "exercises": [{"name": "Extensora", "sets": "10", "weight": "0"}, {"name": "Leg Press 45º", "sets": "10", "weight": "0"}, {"name": "Agachamento smith ou guiado", "sets": "10", "weight": "0"}, {"name": "Agachamento no rack", "sets": "10", "weight": "0"}, {"name": "Adutor", "sets": "10", "weight": "0"}, {"name": "Peck deck", "sets": "9", "weight": "0"}, {"name": "Supino inclinado", "sets": "9", "weight": "0"}, {"name": "Supino reto", "sets": "9", "weight": "0"}, {"name": "Rosca direta ou alternada", "sets": "9", "weight": "0"}  ]},{  "name": "B - Marina",  "date": "2016/06/01",  "duration": "5898",  "repsPerSet": "8-12",  "rest": "39",  "exercises": [{"name": "Flexora", "sets": "7", "weight": "24"}, {"name": "Glúteo em pé", "sets": "7", "weight": "0"}, {"name": "Glúteo no cabo", "sets": "7", "weight": "0"}, {"name": "Abdutor", "sets": "7", "weight": "0"}, {"name": "Agachamento sumo", "sets": "7", "weight": "0"}, {"name": "Stiff", "sets": "7", "weight": "0"}, {"name": "Remada articulada", "sets": "7", "weight": "0"}, {"name": "Tríceps na polia", "sets": "7", "weight": "0"}, {"name": "Tríceps corda", "sets": "7", "weight": "0"}, {"name": "Panturrilha", "sets": "7", "weight": "0"}, {"name": "Puxador frente", "sets": "6", "weight": "0"}, {"name": "Remada baixa", "sets": "6", "weight": "0"}  ]}]}
